streamlit_javascript/__init__.py
streamlit_javascript/frontend/build/asset-manifest.json
streamlit_javascript/frontend/build/bootstrap.min.css
streamlit_javascript/frontend/build/index.html
streamlit_javascript/frontend/build/static/js/2.ec72239e.chunk.js
streamlit_javascript/frontend/build/static/js/2.ec72239e.chunk.js.LICENSE.txt
streamlit_javascript/frontend/build/static/js/2.ec72239e.chunk.js.map
streamlit_javascript/frontend/build/static/js/main.7266a869.chunk.js
streamlit_javascript/frontend/build/static/js/main.7266a869.chunk.js.map
streamlit_javascript/frontend/build/static/js/runtime-main.0d150111.js
streamlit_javascript/frontend/build/static/js/runtime-main.0d150111.js.map
streamlit_javascript-0.1.5.dist-info/LICENSE
streamlit_javascript-0.1.5.dist-info/METADATA
streamlit_javascript-0.1.5.dist-info/WHEEL
streamlit_javascript-0.1.5.dist-info/top_level.txt
streamlit_javascript-0.1.5.dist-info/RECORD
