Metadata-Version: 2.1
Name: streamlit-javascript
Version: 0.1.5
Summary: component to run javascript code in streamlit application
Home-page: https://github.com/thunderbug1/streamlit-javascript
Author: Alexander Balasch
Author-email: 
Classifier: Programming Language :: Python :: 3
Classifier: License :: OSI Approved :: MIT License
Classifier: Operating System :: OS Independent
Requires-Python: >=3.6
License-File: LICENSE
